traffic_forward/__init__.py
traffic_forward-1.0.0.dist-info/DESCRIPTION.rst
traffic_forward-1.0.0.dist-info/METADATA
traffic_forward-1.0.0.dist-info/RECORD
traffic_forward-1.0.0.dist-info/WHEEL
traffic_forward-1.0.0.dist-info/entry_points.txt
traffic_forward-1.0.0.dist-info/metadata.json
traffic_forward-1.0.0.dist-info/top_level.txt
