Metadata-Version: 2.0
Name: traffic-forward
Version: 1.0.0
Summary: This tool is used for forwarding local and remote (intranet) traffic
Home-page: https://github.com/doudoudedi/traffic_forward
Author: doudoudedi
Author-email: doudoudedi233@gmail.com
License: MIT
Platform: UNKNOWN
